{"[": {"x_divide": 52, "y_divide": -80, "width": 105, "top_coord": -221, "bottom_coord": 58}, "'": {"x_divide": 29, "y_divide": -80, "width": 59, "top_coord": -221, "bottom_coord": 0}, " ": {"x_divide": 41, "y_divide": -80, "width": 83, "top_coord": 0, "bottom_coord": 1}, ",": {"x_divide": 41, "y_divide": -80, "width": 83, "top_coord": -40, "bottom_coord": 25}, "!": {"x_divide": 44, "y_divide": -80, "width": 88, "top_coord": -221, "bottom_coord": 4}, "\"": {"x_divide": 46, "y_divide": -80, "width": 93, "top_coord": -221, "bottom_coord": 0}, "#": {"x_divide": 108, "y_divide": -80, "width": 216, "top_coord": -221, "bottom_coord": 0}, "$": {"x_divide": 83, "y_divide": -80, "width": 166, "top_coord": -230, "bottom_coord": 51}, "%": {"x_divide": 116, "y_divide": -80, "width": 232, "top_coord": -223, "bottom_coord": 14}, "&": {"x_divide": 113, "y_divide": -80, "width": 227, "top_coord": -208, "bottom_coord": 5}, "(": {"x_divide": 55, "y_divide": -80, "width": 111, "top_coord": -225, "bottom_coord": 62}, ")": {"x_divide": 55, "y_divide": -80, "width": 111, "top_coord": -225, "bottom_coord": 62}, "*": {"x_divide": 63, "y_divide": -80, "width": 127, "top_coord": -221, "bottom_coord": 0}, "+": {"x_divide": 91, "y_divide": -80, "width": 182, "top_coord": -183, "bottom_coord": 0}, "-": {"x_divide": 50, "y_divide": -80, "width": 100, "top_coord": -90, "bottom_coord": 0}, ".": {"x_divide": 41, "y_divide": -80, "width": 83, "top_coord": -32, "bottom_coord": 4}, "/": {"x_divide": 65, "y_divide": -80, "width": 131, "top_coord": -221, "bottom_coord": 29}, "0": {"x_divide": 83, "y_divide": -80, "width": 166, "top_coord": -220, "bottom_coord": 5}, "1": {"x_divide": 83, "y_divide": -80, "width": 166, "top_coord": -215, "bottom_coord": 0}, "2": {"x_divide": 83, "y_divide": -80, "width": 166, "top_coord": -220, "bottom_coord": 0}, "3": {"x_divide": 83, "y_divide": -80, "width": 166, "top_coord": -220, "bottom_coord": 5}, "4": {"x_divide": 83, "y_divide": -80, "width": 166, "top_coord": -220, "bottom_coord": 0}, "5": {"x_divide": 83, "y_divide": -80, "width": 166, "top_coord": -215, "bottom_coord": 5}, "6": {"x_divide": 83, "y_divide": -80, "width": 166, "top_coord": -220, "bottom_coord": 5}, "7": {"x_divide": 83, "y_divide": -80, "width": 166, "top_coord": -215, "bottom_coord": 5}, "8": {"x_divide": 83, "y_divide": -80, "width": 166, "top_coord": -220, "bottom_coord": 5}, "9": {"x_divide": 83, "y_divide": -80, "width": 166, "top_coord": -220, "bottom_coord": 5}, ":": {"x_divide": 41, "y_divide": -80, "width": 83, "top_coord": -163, "bottom_coord": 4}, ";": {"x_divide": 41, "y_divide": -80, "width": 83, "top_coord": -163, "bottom_coord": 25}, "<": {"x_divide": 91, "y_divide": -80, "width": 182, "top_coord": -187, "bottom_coord": 0}, "=": {"x_divide": 91, "y_divide": -80, "width": 182, "top_coord": -151, "bottom_coord": 0}, ">": {"x_divide": 91, "y_divide": -80, "width": 182, "top_coord": -187, "bottom_coord": 0}, "?": {"x_divide": 88, "y_divide": -80, "width": 177, "top_coord": -221, "bottom_coord": 4}, "@": {"x_divide": 130, "y_divide": -80, "width": 260, "top_coord": -225, "bottom_coord": 4}, "A": {"x_divide": 111, "y_divide": -108, "width": 222, "top_coord": -215, "bottom_coord": 0}, "B": {"x_divide": 86, "y_divide": -108, "width": 172, "top_coord": -215, "bottom_coord": 0}, "C": {"x_divide": 122, "y_divide": -108, "width": 244, "top_coord": -220, "bottom_coord": 5}, "D": {"x_divide": 111, "y_divide": -108, "width": 223, "top_coord": -215, "bottom_coord": 0}, "E": {"x_divide": 80, "y_divide": -108, "width": 161, "top_coord": -215, "bottom_coord": 0}, "F": {"x_divide": 72, "y_divide": -108, "width": 145, "top_coord": -215, "bottom_coord": 0}, "G": {"x_divide": 131, "y_divide": -108, "width": 262, "top_coord": -220, "bottom_coord": 5}, "H": {"x_divide": 102, "y_divide": -108, "width": 205, "top_coord": -215, "bottom_coord": 0}, "I": {"x_divide": 34, "y_divide": -108, "width": 68, "top_coord": -215, "bottom_coord": 0}, "J": {"x_divide": 72, "y_divide": -108, "width": 145, "top_coord": -215, "bottom_coord": 5}, "K": {"x_divide": 88, "y_divide": -108, "width": 177, "top_coord": -215, "bottom_coord": 0}, "L": {"x_divide": 69, "y_divide": -108, "width": 139, "top_coord": -215, "bottom_coord": 0}, "M": {"x_divide": 138, "y_divide": -108, "width": 276, "top_coord": -215, "bottom_coord": 0}, "N": {"x_divide": 111, "y_divide": -108, "width": 222, "top_coord": -215, "bottom_coord": 0}, "O": {"x_divide": 130, "y_divide": -108, "width": 261, "top_coord": -220, "bottom_coord": 5}, "P": {"x_divide": 89, "y_divide": -108, "width": 178, "top_coord": -215, "bottom_coord": 0}, "Q": {"x_divide": 130, "y_divide": -108, "width": 261, "top_coord": -220, "bottom_coord": 17}, "R": {"x_divide": 91, "y_divide": -108, "width": 182, "top_coord": -215, "bottom_coord": 0}, "S": {"x_divide": 74, "y_divide": -108, "width": 149, "top_coord": -220, "bottom_coord": 5}, "T": {"x_divide": 64, "y_divide": -108, "width": 128, "top_coord": -215, "bottom_coord": 0}, "U": {"x_divide": 98, "y_divide": -108, "width": 196, "top_coord": -215, "bottom_coord": 5}, "V": {"x_divide": 105, "y_divide": -108, "width": 211, "top_coord": -215, "bottom_coord": 0}, "W": {"x_divide": 144, "y_divide": -108, "width": 288, "top_coord": -215, "bottom_coord": 0}, "X": {"x_divide": 91, "y_divide": -108, "width": 183, "top_coord": -215, "bottom_coord": 0}, "Y": {"x_divide": 89, "y_divide": -108, "width": 178, "top_coord": -215, "bottom_coord": 0}, "Z": {"x_divide": 72, "y_divide": -108, "width": 144, "top_coord": -215, "bottom_coord": 0}, "\\": {"x_divide": 91, "y_divide": -80, "width": 182, "top_coord": -221, "bottom_coord": 29}, "]": {"x_divide": 52, "y_divide": -80, "width": 105, "top_coord": -221, "bottom_coord": 58}, "^": {"x_divide": 101, "y_divide": -80, "width": 202, "top_coord": -215, "bottom_coord": 0}, "_": {"x_divide": 75, "y_divide": -80, "width": 154, "top_coord": 0, "bottom_coord": 38}, "`": {"x_divide": 56, "y_divide": -80, "width": 113, "top_coord": -234, "bottom_coord": 0}, "a": {"x_divide": 102, "y_divide": -80, "width": 205, "top_coord": -163, "bottom_coord": 4}, "b": {"x_divide": 102, "y_divide": -80, "width": 205, "top_coord": -221, "bottom_coord": 4}, "c": {"x_divide": 97, "y_divide": -80, "width": 194, "top_coord": -163, "bottom_coord": 4}, "d": {"x_divide": 103, "y_divide": -80, "width": 206, "top_coord": -221, "bottom_coord": 4}, "e": {"x_divide": 97, "y_divide": -80, "width": 195, "top_coord": -163, "bottom_coord": 4}, "f": {"x_divide": 47, "y_divide": -80, "width": 94, "top_coord": -225, "bottom_coord": 0}, "g": {"x_divide": 101, "y_divide": -80, "width": 202, "top_coord": -163, "bottom_coord": 62}, "h": {"x_divide": 91, "y_divide": -80, "width": 183, "top_coord": -221, "bottom_coord": 0}, "i": {"x_divide": 30, "y_divide": -80, "width": 60, "top_coord": -225, "bottom_coord": 0}, "j": {"x_divide": 25, "y_divide": -80, "width": 71, "top_coord": -225, "bottom_coord": 62}, "k": {"x_divide": 76, "y_divide": -80, "width": 153, "top_coord": -221, "bottom_coord": 0}, "l": {"x_divide": 30, "y_divide": -80, "width": 60, "top_coord": -221, "bottom_coord": 0}, "m": {"x_divide": 140, "y_divide": -80, "width": 281, "top_coord": -163, "bottom_coord": 0}, "n": {"x_divide": 91, "y_divide": -80, "width": 183, "top_coord": -163, "bottom_coord": 0}, "o": {"x_divide": 98, "y_divide": -80, "width": 196, "top_coord": -163, "bottom_coord": 4}, "p": {"x_divide": 102, "y_divide": -80, "width": 205, "top_coord": -163, "bottom_coord": 58}, "q": {"x_divide": 102, "y_divide": -80, "width": 205, "top_coord": -163, "bottom_coord": 58}, "r": {"x_divide": 48, "y_divide": -80, "width": 96, "top_coord": -163, "bottom_coord": 0}, "s": {"x_divide": 58, "y_divide": -80, "width": 116, "top_coord": -163, "bottom_coord": 4}, "t": {"x_divide": 51, "y_divide": -80, "width": 102, "top_coord": -219, "bottom_coord": 0}, "u": {"x_divide": 91, "y_divide": -80, "width": 182, "top_coord": -159, "bottom_coord": 4}, "v": {"x_divide": 83, "y_divide": -80, "width": 166, "top_coord": -159, "bottom_coord": 0}, "w": {"x_divide": 124, "y_divide": -80, "width": 249, "top_coord": -159, "bottom_coord": 0}, "x": {"x_divide": 72, "y_divide": -80, "width": 148, "top_coord": -159, "bottom_coord": 0}, "y": {"x_divide": 80, "y_divide": -80, "width": 161, "top_coord": -159, "bottom_coord": 58}, "z": {"x_divide": 63, "y_divide": -80, "width": 127, "top_coord": -159, "bottom_coord": 0}, "{": {"x_divide": 52, "y_divide": -80, "width": 105, "top_coord": -215, "bottom_coord": 66}, "|": {"x_divide": 101, "y_divide": -80, "width": 202, "top_coord": -221, "bottom_coord": 58}, "}": {"x_divide": 52, "y_divide": -80, "width": 105, "top_coord": -215, "bottom_coord": 66}, "~": {"x_divide": 91, "y_divide": -80, "width": 182, "top_coord": -130, "bottom_coord": 0}, "\u2018": {"x_divide": 52, "y_divide": -80, "width": 105, "top_coord": -221, "bottom_coord": 0}, "\u2019": {"x_divide": 52, "y_divide": -80, "width": 105, "top_coord": -221, "bottom_coord": 0}, "\u201c": {"x_divide": 75, "y_divide": -80, "width": 151, "top_coord": -221, "bottom_coord": 0}, "\u201d": {"x_divide": 72, "y_divide": -80, "width": 145, "top_coord": -221, "bottom_coord": 0}}